{
    "apps": [
      {
        "name": "vibecheck-server",
        "script": "bun",
        "args": "index.ts",
        "env": {
          "NODE_ENV": "production"
        }
      },
      {
        "name": "vibecheck-audio-worker",
        "script": "bun",
        "args": "src/workers/audio.worker.ts",
        "env": {
          "NODE_ENV": "production"
        }
      },
      {
        "name": "vibecheck-gpt-worker",
        "script": "bun",
        "args": "src/workers/gpt.worker.ts",
        "env": {
          "NODE_ENV": "production"
        }
      }
    ]
  }